mosestokenizer/__init__.py
mosestokenizer/lib/_mosestokenizer.cpython-39-darwin.so
mosestokenizer/share/README.txt
mosestokenizer/share/nonbreaking_prefixes/README.txt
mosestokenizer/share/nonbreaking_prefixes/nonbreaking_prefix.as
mosestokenizer/share/nonbreaking_prefixes/nonbreaking_prefix.bn
mosestokenizer/share/nonbreaking_prefixes/nonbreaking_prefix.ca
mosestokenizer/share/nonbreaking_prefixes/nonbreaking_prefix.cs
mosestokenizer/share/nonbreaking_prefixes/nonbreaking_prefix.de
mosestokenizer/share/nonbreaking_prefixes/nonbreaking_prefix.el
mosestokenizer/share/nonbreaking_prefixes/nonbreaking_prefix.en
mosestokenizer/share/nonbreaking_prefixes/nonbreaking_prefix.es
mosestokenizer/share/nonbreaking_prefixes/nonbreaking_prefix.et
mosestokenizer/share/nonbreaking_prefixes/nonbreaking_prefix.fi
mosestokenizer/share/nonbreaking_prefixes/nonbreaking_prefix.fr
mosestokenizer/share/nonbreaking_prefixes/nonbreaking_prefix.ga
mosestokenizer/share/nonbreaking_prefixes/nonbreaking_prefix.gu
mosestokenizer/share/nonbreaking_prefixes/nonbreaking_prefix.hi
mosestokenizer/share/nonbreaking_prefixes/nonbreaking_prefix.hu
mosestokenizer/share/nonbreaking_prefixes/nonbreaking_prefix.is
mosestokenizer/share/nonbreaking_prefixes/nonbreaking_prefix.it
mosestokenizer/share/nonbreaking_prefixes/nonbreaking_prefix.kn
mosestokenizer/share/nonbreaking_prefixes/nonbreaking_prefix.lt
mosestokenizer/share/nonbreaking_prefixes/nonbreaking_prefix.lv
mosestokenizer/share/nonbreaking_prefixes/nonbreaking_prefix.ml
mosestokenizer/share/nonbreaking_prefixes/nonbreaking_prefix.mni
mosestokenizer/share/nonbreaking_prefixes/nonbreaking_prefix.mr
mosestokenizer/share/nonbreaking_prefixes/nonbreaking_prefix.nl
mosestokenizer/share/nonbreaking_prefixes/nonbreaking_prefix.or
mosestokenizer/share/nonbreaking_prefixes/nonbreaking_prefix.pa
mosestokenizer/share/nonbreaking_prefixes/nonbreaking_prefix.pl
mosestokenizer/share/nonbreaking_prefixes/nonbreaking_prefix.pt
opus_fast_mosestokenizer-0.0.8.11.dist-info/licenses/LICENSE
opus_fast_mosestokenizer-0.0.8.11.dist-info/METADATA
opus_fast_mosestokenizer-0.0.8.11.dist-info/WHEEL
opus_fast_mosestokenizer-0.0.8.11.dist-info/top_level.txt
opus_fast_mosestokenizer-0.0.8.11.dist-info/RECORD
